{
  "type": "Program",
  "start": 0,
  "end": 28,
  "sourceType": "script",
  "interpreter": null,
  "body": [
    {
      "type": "ExpressionStatement",
      "start": 0,
      "end": 28,
      "expression": {
        "type": "FunctionExpression",
        "start": 0,
        "end": 28,
        "generator": false,
        "async": false,
        "arrow": true,
        "params": [
          {
            "type": "Identifier",
            "start": 1,
            "end": 2,
            "name": "x"
          }
        ],
        "body": {
          "type": "FunctionExpression",
          "start": 8,
          "end": 27,
          "generator": false,
          "async": false,
          "arrow": true,
          "params": [
            {
              "type": "Identifier",
              "start": 9,
              "end": 10,
              "name": "y"
            },
            {
              "type": "Identifier",
              "start": 12,
              "end": 13,
              "name": "z"
            }
          ],
          "body": {
            "type": "SequenceExpression",
            "start": 19,
            "end": 26,
            "expressions": [
              {
                "type": "Identifier",
                "start": 19,
                "end": 20,
                "name": "x"
              },
              {
                "type": "Identifier",
                "start": 22,
                "end": 23,
                "name": "y"
              },
              {
                "type": "Identifier",
                "start": 25,
                "end": 26,
                "name": "z"
              }
            ]
          }
        }
      }
    }
  ]
}