{
  "type": "Program",
  "start": 0,
  "end": 9,
  "body": [
    {
      "type": "VariableDeclaration",
      "start": 0,
      "end": 9,
      "declarations": [
        {
          "type": "VariableDeclarator",
          "start": 4,
          "end": 5,
          "id": {
            "type": "Identifier",
            "start": 4,
            "end": 5,
            "name": "x"
          }
        },
        {
          "type": "VariableDeclarator",
          "start": 7,
          "end": 8,
          "id": {
            "type": "Identifier",
            "start": 7,
            "end": 8,
            "name": "y"
          }
        }
      ],
      "kind": "var"
    }
  ]
}